nonebot_plugin_chess/__init__.py
nonebot_plugin_chess/config.py
nonebot_plugin_chess/game.py
nonebot_plugin_chess/migrations/32c01e50814d_init_db.py
nonebot_plugin_chess/model.py
nonebot_plugin_chess-0.5.2.dist-info/LICENSE
nonebot_plugin_chess-0.5.2.dist-info/METADATA
nonebot_plugin_chess-0.5.2.dist-info/WHEEL
nonebot_plugin_chess-0.5.2.dist-info/RECORD
